noveler/__init__.py
noveler/__main__.py
noveler/conftest.py
noveler/main.py
noveler/mcp_server.py
noveler/application/__init__.py
noveler/application/bootstrap.py
noveler/application/bus_handlers.py
noveler/application/dead_letter_queue.py
noveler/application/idempotency.py
noveler/application/message_bus.py
noveler/application/outbox.py
noveler/application/schemas.py
noveler/application/simple_message_bus.py
noveler/application/unit_of_work.py
noveler/application/uow.py
noveler/application/adapters/bus_compatibility_bridge.py
noveler/application/adapters/quality_check_adapter.py
noveler/application/adapters/usecase_bus_adapter.py
noveler/application/ai_integration/__init__.py
noveler/application/ai_integration/use_cases/__init__.py
noveler/application/ai_integration/use_cases/analyze_genre_comparison_use_case.py
noveler/application/ai_integration/use_cases/analyze_plot_use_case.py
noveler/application/base/__init__.py
noveler/application/base/abstract_use_case.py
noveler/application/checkers/foreshadowing_checker.py
noveler/application/dto/scene_management_dto.py
noveler/application/factories/__init__.py
noveler/application/factories/progressive_check_factory.py
noveler/application/handlers/__init__.py
noveler/application/handlers/plot_command_handlers.py
noveler/application/handlers/plot_event_handlers.py
noveler/application/infrastructure_services/__init__.py
noveler/application/infrastructure_services/infrastructure_configuration.py
noveler/application/infrastructure_services/infrastructure_configuration_repository.py
noveler/application/infrastructure_services/infrastructure_coordination_service.py
noveler/application/infrastructure_services/infrastructure_integration_aggregate.py
noveler/application/infrastructure_services/infrastructure_integration_services.py
noveler/application/infrastructure_services/infrastructure_integration_use_case.py
noveler/application/infrastructure_services/service_execution_orchestrator.py
noveler-3.0.0.dist-info/METADATA
noveler-3.0.0.dist-info/WHEEL
noveler-3.0.0.dist-info/RECORD
