Metadata-Version: 2.4
Name: noveler
Version: 3.0.0
Summary: 小説執筆支援システム for なろう系Web小説
Project-URL: Homepage, https://github.com/novel-writing-support/novel-system
Project-URL: Documentation, https://novel-writing-support.readthedocs.io/
Project-URL: Repository, https://github.com/novel-writing-support/novel-system.git
Project-URL: Issues, https://github.com/novel-writing-support/novel-system/issues
Author: Novel Writing Support Team
License: MIT
Keywords: japanese,narou,novel,web-novel,writing
Classifier: Development Status :: 4 - Beta
Classifier: Intended Audience :: Developers
Classifier: License :: OSI Approved :: MIT License
Classifier: Programming Language :: Python :: 3
Classifier: Programming Language :: Python :: 3.10
Classifier: Programming Language :: Python :: 3.11
Classifier: Programming Language :: Python :: 3.12
Classifier: Programming Language :: Python :: 3.13
Classifier: Topic :: Software Development :: Libraries :: Python Modules
Classifier: Topic :: Text Processing :: Markup
Requires-Python: >=3.10
Requires-Dist: deal>=4.24.0
Requires-Dist: janome>=0.4.2
Requires-Dist: jinja2>=3.1.0
Requires-Dist: mcp>=1.13.0
Requires-Dist: numpy>=1.26.0
Requires-Dist: psutil>=5.9.0
Requires-Dist: pyyaml>=6.0
Requires-Dist: requests>=2.28.0
Requires-Dist: rich>=13.0.0
Requires-Dist: ruamel-yaml>=0.18.0
Requires-Dist: yamllint>=1.33.0
Provides-Extra: dev
Requires-Dist: hypothesis>=6.100.0; extra == 'dev'
Requires-Dist: import-linter>=2.0; extra == 'dev'
Requires-Dist: langgraph>=0.6.7; extra == 'dev'
Requires-Dist: mypy>=1.8.0; extra == 'dev'
Requires-Dist: pre-commit>=3.5.0; extra == 'dev'
Requires-Dist: pytest-archon>=0.0.5; extra == 'dev'
Requires-Dist: pytest-asyncio>=0.23.0; extra == 'dev'
Requires-Dist: pytest-cov>=4.0.0; extra == 'dev'
Requires-Dist: pytest-mock>=3.0.0; extra == 'dev'
Requires-Dist: pytest-xdist>=3.5.0; extra == 'dev'
Requires-Dist: pytest>=8.0.0; extra == 'dev'
Requires-Dist: ruff>=0.1.0; extra == 'dev'
Requires-Dist: types-pyyaml>=6.0.0; extra == 'dev'
Requires-Dist: types-requests>=2.31.0; extra == 'dev'
Provides-Extra: lint
Requires-Dist: mypy>=1.8.0; extra == 'lint'
Requires-Dist: pre-commit>=3.5.0; extra == 'lint'
Requires-Dist: ruff>=0.1.0; extra == 'lint'
Requires-Dist: types-pyyaml>=6.0.0; extra == 'lint'
Requires-Dist: types-requests>=2.31.0; extra == 'lint'
Provides-Extra: test
Requires-Dist: hypothesis>=6.100.0; extra == 'test'
Requires-Dist: langgraph>=0.6.7; extra == 'test'
Requires-Dist: pytest-asyncio>=0.23.0; extra == 'test'
Requires-Dist: pytest-cov>=4.0.0; extra == 'test'
Requires-Dist: pytest-mock>=3.0.0; extra == 'test'
Requires-Dist: pytest-timeout>=2.2.0; extra == 'test'
Requires-Dist: pytest-xdist>=3.5.0; extra == 'test'
Requires-Dist: pytest>=8.0.0; extra == 'test'
